lavender/__init__.py
lavender/admin.py
lavender/apps.py
lavender/decorators.py
lavender/forms.py
lavender/models.py
lavender/settings.py
lavender/urls.py
lavender/utils.py
lavender/wsgi.py
lavender/fixtures/auth.yaml
lavender/fixtures/contenttypes.yaml
lavender/fixtures/lavender.yaml
lavender/migrations/0001_initial.py
lavender/migrations/0002_remove_package_version.py
lavender/migrations/0003_texture_metadata.py
lavender/migrations/0004_backfill_texture_metadata.py
lavender/migrations/__init__.py
lavender/views/__init__.py
lavender/views/profile.py
lavender/views/registration.py
lavender/views/api/__init__.py
lavender/views/api/decorator.py
lavender/views/api/packages.py
lavender/views/api/telemetry.py
lavender/views/nidhoggr/__init__.py
lavender/views/nidhoggr/textures.py
lavender/views/nidhoggr/users.py
tests/__init__.py
mc4ep_lavender-0.17.0.dist-info/METADATA
mc4ep_lavender-0.17.0.dist-info/WHEEL
mc4ep_lavender-0.17.0.dist-info/top_level.txt
mc4ep_lavender-0.17.0.dist-info/RECORD
