Metadata-Version: 2.1
Name: mc4ep-lavender
Version: 0.17.0
Summary: MC4EP cabinet core
Home-page: https://git.mc4ep.org/mc4ep/lavender
Author: Andriy Kushnir (Orhideous)
Author-email: me@orhideous.name
License: MIT
Keywords: Minecraft,Yggdrasil,Authentication,Nidhoggr,Lavender
Platform: UNKNOWN
Classifier: Development Status :: 4 - Beta
Classifier: Environment :: No Input/Output (Daemon)
Classifier: Intended Audience :: Developers
Classifier: Intended Audience :: System Administrators
Classifier: License :: OSI Approved
Classifier: License :: OSI Approved :: MIT License
Classifier: Operating System :: OS Independent
Classifier: Programming Language :: Python
Classifier: Programming Language :: Python :: 3
Classifier: Programming Language :: Python :: 3.6
Classifier: Programming Language :: Python :: 3.7
Classifier: Programming Language :: Python :: Implementation :: CPython
Classifier: Programming Language :: Python :: Implementation :: PyPy
Classifier: Topic :: Internet :: WWW/HTTP :: WSGI
Classifier: Topic :: Internet :: WWW/HTTP :: WSGI :: Application
Classifier: Topic :: Utilities
Requires-Dist: Django (==2.2.18)
Requires-Dist: mysqlclient (==2.0.3)
Requires-Dist: django-debug-toolbar (==2.2)
Requires-Dist: django-jsonfield-backport (==1.0.3)
Requires-Dist: Pillow (==8.1.0)
Requires-Dist: singleton-decorator (==1.0.0)
Requires-Dist: pydantic (==1.7.3)
Requires-Dist: nidhoggr-core (>=0.10)
Requires-Dist: sps-parser (>=0.3)
Requires-Dist: django-json-widget (==1.1.1)
